CHANGELOG.md
LICENSE.Apache.v2
LICENSE.GPL.v2
MANIFEST.in
README.license.md
README.rst
VERSION
setup.cfg
setup.py
pr2modules/__init__.py
pr2modules/cli/__init__.py
pr2modules/cli/console.py
pr2modules/cli/parser.py
pr2modules/cli/server.py
pr2modules/cli/session.py
pr2modules/cli/auth/__init__.py
pr2modules/cli/auth/auth_keystone.py
pr2modules/cli/auth/auth_radius.py
pr2modules/ndb/__init__.py
pr2modules/ndb/auth_manager.py
pr2modules/ndb/cli.py
pr2modules/ndb/cluster.py
pr2modules/ndb/events.py
pr2modules/ndb/main.py
pr2modules/ndb/messages.py
pr2modules/ndb/noipdb.py
pr2modules/ndb/query.py
pr2modules/ndb/report.py
pr2modules/ndb/schema.py
pr2modules/ndb/source.py
pr2modules/ndb/transaction.py
pr2modules/ndb/transport.py
pr2modules/ndb/view.py
pr2modules/ndb/objects/__init__.py
pr2modules/ndb/objects/address.py
pr2modules/ndb/objects/interface.py
pr2modules/ndb/objects/neighbour.py
pr2modules/ndb/objects/netns.py
pr2modules/ndb/objects/route.py
pr2modules/ndb/objects/rule.py
pyroute2.ndb.egg-info/PKG-INFO
pyroute2.ndb.egg-info/SOURCES.txt
pyroute2.ndb.egg-info/dependency_links.txt
pyroute2.ndb.egg-info/entry_points.txt
pyroute2.ndb.egg-info/namespace_packages.txt
pyroute2.ndb.egg-info/requires.txt
pyroute2.ndb.egg-info/top_level.txt